flagg/__init__.py
flagg/__main__.py
flagg/interface/__init__.py
flagg/interface/lexer.py
flagg/interface/parser.py
flagg/interface/symbol_table.py
flagg/utils/dataclasses.py
flagg/utils/errors.py
flagg-0.2.3.dist-info/WHEEL
flagg-0.2.3.dist-info/METADATA
flagg-0.2.3.dist-info/RECORD
