Metadata-Version: 2.1
Name: flagg
Version: 0.2.3
Summary: Formal Languages Analyzer Generator
Author: João Vitor Maia
Author-email: maia.tostring@gmail.com
Requires-Python: >=3.10,<4.0
Classifier: Programming Language :: Python :: 3
Classifier: Programming Language :: Python :: 3.10
Requires-Dist: autome (==0.2.2)
Requires-Dist: click (>=8.1.3,<9.0.0)
